experiment_utils.py
experiment_utils_alt.py
Coupled-VAE/GeneralizedMean.py
Coupled-VAE/Sampler_Z.py
Coupled-VAE/VAECIFAR.py
Coupled-VAE/VAEMNIST.py
Coupled-VAE/VAEModelCIFAR.py
Coupled-VAE/VAEModelMNIST.py
Coupled-VAE/Visualize.py
Coupled-VAE/__init__.py
Coupled-VAE/experiment_utils.py
Coupled-VAE/setup_funcs.py
coupled_vae/experiment_utils.py
coupled_vae/papers/python/Test.py
coupled_vae/papers/python/mnist_data.py
coupled_vae/papers/python/run_main.py
coupled_vae/papers/python/vae.py
coupled_vae-0.0.1.dist-info/METADATA
coupled_vae-0.0.1.dist-info/WHEEL
coupled_vae-0.0.1.dist-info/licenses/LICENSE
coupled_vae-0.0.1.dist-info/licenses/LICENSE.txt
coupled_vae-0.0.1.dist-info/RECORD
