Metadata-Version: 2.1
Name: Coupled-VAE
Version: 0.0.1
Summary: Package holding code for Coupled VAE paper.
Project-URL: Homepage, https://github.com/Photrek/Coupled-VAE
Project-URL: Bug Tracker, https://github.com/Photrek/Coupled-VAE/issues
Author-email: John Clements <jkclements2016@gmail.com>
License:                     GNU GENERAL PUBLIC LICENSE
License-File: LICENSE
License-File: LICENSE.txt
Keywords: coupling,vae,variational auto-encoder
Classifier: Operating System :: OS Independent
Classifier: Programming Language :: Python :: 3
Requires-Python: >=3.6
Requires-Dist: matplotlib
Requires-Dist: nsc-tf
Requires-Dist: numpy
Requires-Dist: pandas
Requires-Dist: pathlib
Requires-Dist: sklearn
Requires-Dist: tensorflow
Requires-Dist: tensorflow-datasets
Requires-Dist: tqdm
